setup.py
txairbrake/__init__.py
txairbrake/observers.py
txairbrake.egg-info/PKG-INFO
txairbrake.egg-info/SOURCES.txt
txairbrake.egg-info/dependency_links.txt
txairbrake.egg-info/requires.txt
txairbrake.egg-info/top_level.txt
txairbrake/tests/__init__.py
txairbrake/tests/test_observer.py