Metadata-Version: 1.0
Name: txairbrake
Version: 0.4
Summary: txairbrake reports exceptions in Twisted code to an airbrake server
Home-page: http://github.com/bmuller/txairbrake
Author: Brian Muller
Author-email: bamuller@gmail.com
License: MIT
Platform: UNKNOWN
